<?xml version="1.0" encoding="iso-8859-1"?>
<ship name="Incom T-65 X-Wing" short="X-Wing">
	<comments>
		firerate is ms between shots per cannon
	    the number of firepods must match the count
		order is the order in which the pods will fire if set to alternate-single fire mode 
		offsets are where the actual shot is created from, ie: the end of the barre
		offsets are from the center middle back of the craft, facing forward, in meters
		-x is left, +x is right, -y is up, +y is down, -z is behind, +z is into the screen
	</comments>
	<description>
		The Incom T-65 X-Wing is the main space superiority fighter of the Rebel Alliance and the New Republic.
	</description>
	<physical>
		<width value="10.35" />
		<length value="12.5" />
		<height value="2.85" />
		<mass value="10" />
	</physical>
	<engine>
		<topspeed value="100" />
		<maxthrust value="5" />
		<maxaclthrust value="0.2" />
	</engine>
	<handling>
		<drag value="0.95" />
		<turnrate value="3" />
	</handling>
	<armaments>
		<mainweapon count="4" type="blaster" firerate="250" velocity="700" maxammo="0" power="10">
			<firepod visiblename="UpperLeft" x="-6.25" y="-1.425" z="6.8" />
			<firepod visiblename="LowerRight" x="6.25" y="1.425" z="6.8" />
			<firepod visiblename="LowerLeft" x="-6.25" y="1.425" z="6.8" />
			<firepod visiblename="UpperRight" x="6.25" y="-1.425" z="6.8" />
		</mainweapon>
		<secondaryweapon count="2" type="launcher" maxammo="3">
			<firepod order="0" visiblename="Left" x="-0.5" y="0.25" z="11.75" />
			<firepod order="1" visiblename="Right" x="0.5" y="0.25" z="11.75" />
		</secondaryweapon>
		<options>
			<defaultfiremode value="single" />
		</options>
	</armaments>
	<visuals>
		<cockpit>
			<panel src="XWingCockpitMC.swf" />
		</cockpit>
		<external type="ase">
			<model src="xwing.ASE" />
			<texture src="xwingskin.jpg" />
		</external>
	</visuals>
</ship>